README.md
setup.cfg
setup.py
PipAssimp/__init__.py
PipAssimp/core.py
PipAssimp/errors.py
PipAssimp/formats.py
PipAssimp/helper.py
PipAssimp/libassimp.so.5.0.1
PipAssimp/material.py
PipAssimp/postprocess.py
PipAssimp/structs.py
PipAssimp.egg-info/PKG-INFO
PipAssimp.egg-info/SOURCES.txt
PipAssimp.egg-info/dependency_links.txt
PipAssimp.egg-info/requires.txt
PipAssimp.egg-info/top_level.txt