Metadata-Version: 1.1
Name: PipAssimp
Version: 1.0.5
Summary: Conveniece pkg for install assimp/pyassimp from requirements.txt
Home-page: https://github.com/jameslford/PipAssimp
Author: James Ford
Author-email: jameslford8@gmail.com
License: MIT
Download-URL: https://github.com/jameslford/PipAssimp/archive/v0.0.1.tar.gz
Keywords: 3D,File Conversion,gltf,glb,obj
Platform: UNKNOWN
Classifier: Development Status :: 3 - Alpha
Classifier: Intended Audience :: Developers
Classifier: Topic :: Software Development :: Build Tools
Classifier: License :: OSI Approved :: MIT License
Classifier: Programming Language :: Python :: 3
Classifier: Programming Language :: Python :: 3.4
Classifier: Programming Language :: Python :: 3.5
Classifier: Programming Language :: Python :: 3.6
